{
  "id": "code-mergek-daily-transaction-batch",
  "type": "code",
  "section": "gca-module-2-data-manipulation",
  "title": {
    "en": "Merge daily transaction batches",
    "es": "Mezclar lotes de transacciones diarias"
  },
  "difficulty": "medium",
  "language": "java",
  "statement": {
    "en": "A payment processor receives sorted batches of transaction amounts (in cents) from multiple sources — each day's batch arrives already sorted ascending. Given `int[][] dailyBatches` where each inner array is one day's sorted batch of transaction amounts, return a single `int[]` containing **all amounts merged in globally ascending order**.\n\nThis is functionally identical to a standard k-sorted-arrays merge, applied to a banking domain. Use a **min-heap of cursor tuples** `{amount, batchIdx, positionInBatch}`. Initialize with the first element of each non-empty batch; on each poll, push the next element from the same batch (if any).\n\n**Tiebreaker:** equal amounts across different batches are ordered by **batch index ascending** (the natural compound comparator behavior).\n\nConstraints:\n- `dailyBatches` may be empty (return `new int[]{}`).\n- Individual batches may be empty — must not crash.\n- All amounts are positive integers (cents).\n\nSignature: `public int[] mergeBatches(int[][] dailyBatches)`\n\nExample: `[[99, 199, 500],[250, 300],[150, 400, 1000]]` → `[99, 150, 199, 250, 300, 400, 500, 1000]`",
    "es": "Un procesador de pagos recibe lotes de transacciones ordenados desde múltiples fuentes — el lote de cada día llega ya ordenado de forma ascendente. Dado `int[][] dailyBatches` donde cada arreglo interno es el lote ordenado de montos de transacciones de un día (en centavos), devuelve un único `int[]` con **todos los montos mezclados en orden global ascendente**.\n\nEsto es funcionalmente idéntico a una mezcla estándar de k arreglos ordenados, aplicado al dominio bancario. Usa un **min-heap de tuplas cursor** `{monto, índiceLote, posiciónEnLote}`. Inicializa con el primer elemento de cada lote no vacío; en cada extracción (`poll`), inserta el siguiente elemento del mismo lote (si existe).\n\n**Desempate:** montos iguales de diferentes lotes se ordenan por **índice de lote ascendente** (comportamiento natural del comparador compuesto).\n\nRestricciones:\n- `dailyBatches` puede ser vacío (devuelve `new int[]{}`).\n- Los lotes individuales pueden ser vacíos — no debe lanzar excepción.\n- Todos los montos son enteros positivos (centavos).\n\nFirma: `public int[] mergeBatches(int[][] dailyBatches)`\n\nEjemplo: `[[99, 199, 500],[250, 300],[150, 400, 1000]]` → `[99, 150, 199, 250, 300, 400, 500, 1000]`"
  },
  "starterCode": "import java.util.*;\n\nclass Solution {\n    public int[] mergeBatches(int[][] dailyBatches) {\n        // TODO\n        return new int[]{};\n    }\n}\n",
  "testCode": "import org.junit.jupiter.api.Test;\nimport static org.junit.jupiter.api.Assertions.*;\nimport java.util.*;\n\npublic class SolutionTest {\n\n    @Test\n    void realisticAmounts() {\n        // typical banking scenario with varied transaction amounts in cents\n        assertArrayEquals(\n            new int[]{99, 150, 199, 250, 300, 400, 500, 1000},\n            new Solution().mergeBatches(\n                new int[][]{{99, 199, 500},{250, 300},{150, 400, 1000}})\n        );\n    }\n\n    @Test\n    void singleBatch() {\n        // k=1: one day's batch returned unchanged\n        assertArrayEquals(\n            new int[]{100, 200, 300},\n            new Solution().mergeBatches(new int[][]{{100, 200, 300}})\n        );\n    }\n\n    @Test\n    void emptyBatchAmongOthers() {\n        // one day had zero transactions — must not crash\n        assertArrayEquals(\n            new int[]{50, 75, 120, 300},\n            new Solution().mergeBatches(new int[][]{{50, 120},{},{75, 300}})\n        );\n    }\n\n    @Test\n    void emptyInput() {\n        // no batches at all\n        assertArrayEquals(\n            new int[]{},\n            new Solution().mergeBatches(new int[][]{})\n        );\n    }\n\n    @Test\n    void twoBatchesSameAmounts() {\n        // duplicate amounts across batches; lower batch index appears first\n        // batch0 has 500, batch1 has 500 -> [500, 500, 750]\n        assertArrayEquals(\n            new int[]{500, 500, 750},\n            new Solution().mergeBatches(new int[][]{{500},{500, 750}})\n        );\n    }\n\n    @Test\n    void largeMixedBatches() {\n        // five single-element batches of varying amounts\n        assertArrayEquals(\n            new int[]{10, 20, 30, 40, 50},\n            new Solution().mergeBatches(new int[][]{{30},{10},{50},{20},{40}})\n        );\n    }\n\n    @Test\n    void allBatchesEmpty() {\n        // multiple batches, all empty\n        assertArrayEquals(\n            new int[]{},\n            new Solution().mergeBatches(new int[][]{{},{},{}})\n        );\n    }\n}\n"
}
